tests/TestHelpers.py
tests/__init__.py
tests/implementation/__init__.py
tests/implementation/column/TestCheckColumnDateutilParsable.py
tests/implementation/column/TestCheckColumnStringLengthBetween.py
tests/implementation/column/TestCheckColumnStringLengthEqual.py
tests/implementation/column/TestCheckColumnStringMatchRegex.py
tests/implementation/column/TestCheckColumnStringMatchStrfFormat.py
tests/implementation/column/TestCheckColumnStringNotMatchRegex.py
tests/implementation/column/TestCheckColumnValuesAllNull.py
tests/implementation/column/TestCheckColumnValuesAllSame.py
tests/implementation/column/TestCheckColumnValuesBetween.py
tests/implementation/column/TestCheckColumnValuesDecreasing.py
tests/implementation/column/TestCheckColumnValuesInSet.py
tests/implementation/column/TestCheckColumnValuesIncreasing.py
tests/implementation/column/TestCheckColumnValuesNotInSet.py
tests/implementation/column/TestCheckColumnValuesNotNull.py
tests/implementation/column/TestCheckColumnValuesUnique.py
tests/implementation/column/__init__.py
tests/implementation/table/TestCheckColumnsCountBetween.py
tests/implementation/table/TestCheckColumnsCountExact.py
tests/implementation/table/TestCheckColumnsExists.py
tests/implementation/table/TestCheckColumnsMatchOrderedList.py
tests/implementation/table/TestCheckRowsCountBetween.py
tests/implementation/table/TestCheckRowsCountExact.py
tests/implementation/table/__init__.py
unswamp/__init__.py
unswamp/objects/__init__.py
unswamp/objects/base/DatetimeHandler.py
unswamp/objects/base/MetaDataObject.py
unswamp/objects/base/SerializableObject.py
unswamp/objects/base/__init__.py
unswamp/objects/checks/CheckFunctions.py
unswamp/objects/checks/__init__.py
unswamp/objects/checks/base/BaseArgumentsCheck.py
unswamp/objects/checks/base/BaseCheck.py
unswamp/objects/checks/base/BaseExpectationCheck.py
unswamp/objects/checks/base/BaseFunctionCheck.py
unswamp/objects/checks/base/FunctionCheck.py
unswamp/objects/checks/base/__init__.py
unswamp-1.0.7.2.2.dist-info/LICENSE
unswamp-1.0.7.2.2.dist-info/METADATA
unswamp-1.0.7.2.2.dist-info/WHEEL
unswamp-1.0.7.2.2.dist-info/top_level.txt
unswamp-1.0.7.2.2.dist-info/RECORD
