Metadata-Version: 2.1
Name: unswamp
Version: 1.0.7.2.2
Summary: A python package for data quality unit testing.
Home-page: https://gitlab.com/debugair/unswamp
Author: Stefan Kaspar
Author-email: me@fullbox.ch
License: UNKNOWN
Project-URL: Bug Reports, https://gitlab.com/debugair/unswamp/-/issues
Project-URL: Source, https://gitlab.com/debugair/unswamp
Keywords: data,quality,test,unittest
Platform: UNKNOWN
Classifier: Development Status :: 3 - Alpha
Classifier: Intended Audience :: Developers
Classifier: Topic :: Software Development :: Quality Assurance
Classifier: Programming Language :: Python :: 3.6
Classifier: Programming Language :: Python :: 3.7
Classifier: Programming Language :: Python :: 3.8
Classifier: Programming Language :: Python :: 3.9
Classifier: License :: OSI Approved :: MIT License
Classifier: Operating System :: OS Independent
Requires-Python: >=3.6
License-File: LICENSE
